README.md
setup.py
cpyvke/__init__.py
cpyvke/cpyvke.py
cpyvke/kd5.py
cpyvke/launch.py
cpyvke.egg-info/PKG-INFO
cpyvke.egg-info/SOURCES.txt
cpyvke.egg-info/dependency_links.txt
cpyvke.egg-info/entry_points.txt
cpyvke.egg-info/requires.txt
cpyvke.egg-info/top_level.txt
cpyvke/curseswin/__init__.py
cpyvke/curseswin/app.py
cpyvke/curseswin/classwin.py
cpyvke/curseswin/explorerwin.py
cpyvke/curseswin/kernelwin.py
cpyvke/curseswin/mainwin.py
cpyvke/curseswin/prompt.py
cpyvke/curseswin/widgets.py
cpyvke/objects/__init__.py
cpyvke/objects/pad.py
cpyvke/objects/panel.py
cpyvke/utils/__init__.py
cpyvke/utils/ascii.py
cpyvke/utils/colors.py
cpyvke/utils/comm.py
cpyvke/utils/config.py
cpyvke/utils/daemon3x.py
cpyvke/utils/display.py
cpyvke/utils/inspector.py
cpyvke/utils/kd.py
cpyvke/utils/kernel.py
cpyvke/utils/sockets.py
cpyvke/utils/term_colors.py