Metadata-Version: 1.1
Name: cpyvke
Version: 1.2.4
Summary: A Kernel and variable explorer in Curses
Home-page: https://github.com/ipselium/cpyvke
Author: Cyril Desjouy
Author-email: ipselium@free.fr
License: GPL
Platform: UNKNOWN
Classifier: Development Status :: 4 - Beta
Classifier: Environment :: Console
Classifier: Intended Audience :: Developers
Classifier: Programming Language :: Python
Classifier: Programming Language :: Python :: 3.5
Classifier: License :: OSI Approved :: GNU General Public License v3 or later (GPLv3+)
Classifier: Operating System :: POSIX :: Linux
Classifier: Topic :: Software Development :: Debuggers
